montykit/__init__.py
montykit/analysis.py
montykit/ciphers.py
montykit/converters.py
montykit/generator.py
montykit/girl_boy_names.json
montykit/hash.py
montykit/last_names.json
montykit/middle_names.json
montykit/validators.py
montykit-0.1.0.dist-info/licenses/LICENSE
montykit-0.1.0.dist-info/METADATA
montykit-0.1.0.dist-info/WHEEL
montykit-0.1.0.dist-info/top_level.txt
montykit-0.1.0.dist-info/RECORD
