Metadata-Version: 2.4
Name: montykit
Version: 0.1.0
Summary: A general-purpose Python utility kit.
Author-email: Tyler <tyleruploadspython@gmail.com>
License: MIT
Project-URL: Homepage, https://github.com/tyleruploads/montykit
Project-URL: Source, https://github.com/tyleruploads/montykit
Project-URL: Issues, https://github.com/tyleruploads/montykit/issues
Keywords: utilities,tools,helpers,monty,general-purpose
Classifier: Programming Language :: Python :: 3
Classifier: License :: OSI Approved :: MIT License
Classifier: Operating System :: OS Independent
Classifier: Development Status :: 4 - Beta
Classifier: Intended Audience :: Developers
Requires-Python: >=3.9
License-File: LICENSE
Requires-Dist: textblob>=0.17
Requires-Dist: textstat>=0.7
Dynamic: license-file
